{
  "klass": "v1/transaction",
  "id": 160001,
  "reference": "trx_8H8_1648228936786",
  "amount": 3000,
  "description": "Acheter de cours en ligne sur Educ-Pro academy",
  "callback_url": "https://sandbox-checkout.fedapay.com/transactions/callback?secured_id=&secured_id=secured_id_3m6kmnm3z",
  "status": "approved",
  "customer_id": 2222,
  "currency_id": 1,
  "mode": "mtn",
  "operation": "payment",
  "metadata": {
    "paid_customer": {
      "id": 2222,
      "firstname": "Educ 1",
      "lastname": "byacoubou@africanschoolofeconomics.com",
      "email": "byacoubou@africanschoolofeconomics.com",
      "account_id": 1298,
      "deleted_at": null,
      "created_at": "2020-09-03T10:25:55.772Z",
      "updated_at": "2022-03-23T15:33:57.175Z",
      "phone_number_id": null
    }
  },
  "commission": "0.029",
  "fees": 87,
  "fixed_commission": 0,
  "amount_transferred": 2913,
  "created_at": "2022-03-25T17:22:16.778Z",
  "updated_at": "2022-03-25T17:22:25.484Z",
  "approved_at": "2022-03-25T17:22:24.150Z",
  "canceled_at": null,
  "declined_at": null,
  "refunded_at": null,
  "transferred_at": null,
  "deleted_at": null,
  "last_error_code": "API_ERROR",
  "custom_metadata": null,
  "amount_debited": 3000,
  "receipt_url": "https://sandbox-api.fedapay.com/v1/transactions/receipt?token=eyJ0eXAiOiJKV1QiLCJhbGciOiJIUzI1NiJ9.eyJzdWIiOjE2MDAwMSwiZXhwIjoxNjQ4MzE1MzQ0fQ.vz4_8nXNBX6BU6lvorh5mPHKRVYlCofmsOCueJORi1o",
  "payment_method_id": 15613,
  "sub_accounts_commissions": null,
  "transaction_key": null,
  "customer": {
    "klass": "v1/customer",
    "id": 2222,
    "firstname": "Educ 1",
    "lastname": "byacoubou@africanschoolofeconomics.com",
    "full_name": "Educ 1 byacoubou@africanschoolofeconomics.com",
    "email": "byacoubou@africanschoolofeconomics.com",
    "account_id": 1298,
    "created_at": "2020-09-03T10:25:55.772Z",
    "updated_at": "2022-03-23T15:33:57.175Z",
    "deleted_at": null
  }
},


{
  "klass": "v1/transaction",
  "id": 159866,
  "reference": "trx_8Q4_1648053126729",
  "amount": 3000,
  "description": "Acheter de cours en ligne sur Educ-Pro academy",
  "callback_url": "https://sandbox-checkout.fedapay.com/transactions/callback?secured_id=&secured_id=secured_id_kbqpxvfl5",
  "status": "approved",
  "customer_id": 2222,
  "currency_id": 1,
  "mode": "mtn",
  "operation": "payment",
  "metadata": {
    "paid_customer": {
      "id": 2222,
      "firstname": "Educ 1",
      "lastname": "byacoubou@africanschoolofeconomics.com",
      "email": "byacoubou@africanschoolofeconomics.com",
      "account_id": 1298,
      "deleted_at": null,
      "created_at": "2020-09-03T10:25:55.772Z",
      "updated_at": "2022-03-23T15:33:57.175Z",
      "phone_number_id": null
    }
  },
  "commission": "0.029",
  "fees": 87,
  "fixed_commission": 0,
  "amount_transferred": 2913,
  "created_at": "2022-03-23T16:32:06.729Z",
  "updated_at": "2022-03-23T16:32:20.180Z",
  "approved_at": "2022-03-23T16:32:19.723Z",
  "canceled_at": null,
  "declined_at": null,
  "refunded_at": null,
  "transferred_at": null,
  "deleted_at": null,
  "last_error_code": "API_ERROR",
  "custom_metadata": null,
  "amount_debited": 3000,
  "receipt_url": "https://sandbox-api.fedapay.com/v1/transactions/receipt?token=eyJ0eXAiOiJKV1QiLCJhbGciOiJIUzI1NiJ9.eyJzdWIiOjE1OTg2NiwiZXhwIjoxNjQ4MTM5NTM5fQ.z0gYAnrAg5Iw9GW-B6BBasOWWQ2m_iRiK27Z29sImpI",
  "payment_method_id": 15504,
  "sub_accounts_commissions": null,
  "transaction_key": null,
  "customer": {
    "klass": "v1/customer",
    "id": 2222,
    "firstname": "Educ 1",
    "lastname": "byacoubou@africanschoolofeconomics.com",
    "full_name": "Educ 1 byacoubou@africanschoolofeconomics.com",
    "email": "byacoubou@africanschoolofeconomics.com",
    "account_id": 1298,
    "created_at": "2020-09-03T10:25:55.772Z",
    "updated_at": "2022-03-23T15:33:57.175Z",
    "deleted_at": null
  }
}